pytest_django/__init__.py
pytest_django/_version.py
pytest_django/asserts.py
pytest_django/django_compat.py
pytest_django/fixtures.py
pytest_django/lazy_django.py
pytest_django/live_server_helper.py
pytest_django/plugin.py
pytest_django/py.typed
pytest_django-4.9.0.dist-info/AUTHORS
pytest_django-4.9.0.dist-info/LICENSE
pytest_django-4.9.0.dist-info/METADATA
pytest_django-4.9.0.dist-info/WHEEL
pytest_django-4.9.0.dist-info/entry_points.txt
pytest_django-4.9.0.dist-info/top_level.txt
pytest_django-4.9.0.dist-info/RECORD
