Metadata-Version: 2.1
Name: pytest-django
Version: 4.9.0
Summary: A Django plugin for pytest.
Author-email: Andreas Pelme <andreas@pelme.se>
Maintainer-email: Andreas Pelme <andreas@pelme.se>
License: pytest-django is released under the BSD (3-clause) license
Project-URL: Documentation, https://pytest-django.readthedocs.io/
Project-URL: Repository, https://github.com/pytest-dev/pytest-django
Project-URL: Changelog, https://pytest-django.readthedocs.io/en/latest/changelog.html
Classifier: Development Status :: 5 - Production/Stable
Classifier: Framework :: Django
Classifier: Framework :: Django :: 4.2
Classifier: Framework :: Django :: 5.0
Classifier: Framework :: Django :: 5.1
Classifier: Intended Audience :: Developers
Classifier: License :: OSI Approved :: BSD License
Classifier: Operating System :: OS Independent
Classifier: Programming Language :: Python
Classifier: Programming Language :: Python :: 3.8
Classifier: Programming Language :: Python :: 3.9
Classifier: Programming Language :: Python :: 3.10
Classifier: Programming Language :: Python :: 3.11
Classifier: Programming Language :: Python :: 3.12
Classifier: Programming Language :: Python :: Implementation :: CPython
Classifier: Programming Language :: Python :: Implementation :: PyPy
Classifier: Topic :: Software Development :: Testing
Requires-Python: >=3.8
License-File: LICENSE
License-File: AUTHORS
Requires-Dist: pytest>=7.0.0
Provides-Extra: docs
Requires-Dist: sphinx; extra == "docs"
Requires-Dist: sphinx_rtd_theme; extra == "docs"
Provides-Extra: testing
Requires-Dist: Django; extra == "testing"
Requires-Dist: django-configurations>=2.0; extra == "testing"
